paf_sapgui/__init__.py
paf_sapgui/button.py
paf_sapgui/careview.py
paf_sapgui/checkbox.py
paf_sapgui/element.py
paf_sapgui/elements/__init__.py
paf_sapgui/elements/search_window.py
paf_sapgui/elements/search_window_results.py
paf_sapgui/field/__init__.py
paf_sapgui/field/types.py
paf_sapgui/key.py
paf_sapgui/label.py
paf_sapgui/menubar.py
paf_sapgui/program.py
paf_sapgui/radiobutton.py
paf_sapgui/se16.py
paf_sapgui/selection_screen/__init__.py
paf_sapgui/selection_screen/elements.py
paf_sapgui/session/__init__.py
paf_sapgui/session/active.py
paf_sapgui/session/types.py
paf_sapgui/statusbar/__init__.py
paf_sapgui/statusbar/message.py
paf_sapgui/tab.py
paf_sapgui/table/__init__.py
paf_sapgui/table/elements/__init__.py
paf_sapgui/table/elements/search_window.py
paf_sapgui/table/elements/search_window_results.py
paf_sapgui/table/elements/table.py
paf_sapgui/textfield.py
paf_sapgui/transaction/__init__.py
paf_sapgui/transaction/elements.py
paf_sapgui/window.py
paf_sapgui-1.0.53.dist-info/WHEEL
paf_sapgui-1.0.53.dist-info/METADATA
paf_sapgui-1.0.53.dist-info/RECORD
